setup.cfg
setup.py
ariane_clip3/__init__.py
ariane_clip3/directory.py
ariane_clip3/domino.py
ariane_clip3/driver_common.py
ariane_clip3/driver_factory.py
ariane_clip3/exceptions.py
ariane_clip3/injector.py
ariane_clip3/mapping.py
ariane_clip3.egg-info/PKG-INFO
ariane_clip3.egg-info/SOURCES.txt
ariane_clip3.egg-info/dependency_links.txt
ariane_clip3.egg-info/requires.txt
ariane_clip3.egg-info/top_level.txt
ariane_clip3.egg-info/zip-safe
ariane_clip3/rabbitmq/__init__.py
ariane_clip3/rabbitmq/driver.py
ariane_clip3/rest/__init__.py
ariane_clip3/rest/driver.py
ariane_clip3/zeromq/__init__.py
ariane_clip3/zeromq/driver.py