Metadata-Version: 1.1
Name: ariane-clip3
Version: 0.1.4
Summary: Ariane Python API Library
Home-page: https://github.com/echinopsii/net.echinopsii.ariane.community.cli.python3.git
Author: Mathilde Ffrench
Author-email: mathilde.ffrench@echinopsii.net
License: AGPLv3
Download-URL: https://github.com/echinopsii/net.echinopsii.ariane.community.cli.python3.git/tarball/0.1.4
Platform: UNKNOWN
Classifier: Development Status :: 4 - Beta
Classifier: Intended Audience :: Developers
Classifier: License :: OSI Approved :: GNU Affero General Public License v3
Classifier: License :: OSI Approved :: GNU Affero General Public License v3 or later (AGPLv3+)
Classifier: Natural Language :: English
Classifier: Operating System :: OS Independent
Classifier: Programming Language :: Python :: 3.2
Classifier: Programming Language :: Python :: Implementation :: CPython
Classifier: Topic :: Communications
Classifier: Topic :: Internet
Classifier: Topic :: Software Development :: Libraries
Classifier: Topic :: Software Development :: Libraries :: Python Modules
Classifier: Topic :: System :: Monitoring
Classifier: Topic :: System :: Networking
